{"stem":"1971","instances":[{"docId":"822-16-11","docUri":"822-16-11.html","score":4,"contexts":[{"form":"1971","weight":"1","pos":864,"context":"...1918 bis 1938, 2 Bd., Frankfurt am Main <mark>1971<\/mark>. Otto Weiß: Kulturkatholizismus. Katholiken auf dem...","fid":"note__1"},{"form":"1971","weight":"1","pos":978,"context":"...1918 bis 1938, Band 1, Frankfurt am Main <mark>1971<\/mark>, S. 208-212.","fid":"note__1"},{"form":"1971","weight":"1","pos":1054,"context":"...1918 bis 1938, Band 1, Frankfurt am Main <mark>1971<\/mark>, S. 212-216. Franz Kapfhammer:...","fid":"note__2"},{"form":"1971","weight":"1","pos":1208,"context":"...1918 bis 1938, Band 1, Frankfurt am Main <mark>1971<\/mark>, S. 234-238.","fid":"note__1"}]}]}