{"stem":"abbandonar","instances":[{"docId":"nbr__852-25-44","docUri":"nbr__852-25-44.html","score":1,"contexts":[{"form":"abbandonare","weight":"1","pos":431,"context":"...Federale Mgr. Seipel doveva indurre i socialisti ad <mark>abbandonare<\/mark> l’idea della immediata elezione popolare in cui tanto avevano...","fid":"p__10"}]},{"docId":"nbr__852-23-73","docUri":"nbr__852-23-73.html","score":1,"contexts":[{"form":"abbandonare","weight":"1","pos":618,"context":".... Seipel, alquanto abbattuto, aveva risoluto di <mark>abbandonare<\/mark> il Governo e probabilmente anche la direzione dei cristiano...","fid":"p__17"}]}]}