{"stem":"agostino","instances":[{"docId":"869-33-43","docUri":"869-33-43.html","score":1,"contexts":[{"form":"Agostino","weight":"1","pos":448,"context":"...benedizione apostolica. Della Santità Vostra Umilissimo Obbedientissimo Devotissimo <mark>Agostino<\/mark> Bea 5 ","fid":"page"}]},{"docId":"869-33-42","docUri":"869-33-42.html","score":1,"contexts":[{"form":"Agostino","weight":"1","pos":109,"context":"...ossequi, dell’Eccellenza Vostra Rev.ma dev.mo servitore <mark>Agostino<\/mark> Bea S.J. Preside del Pont. Istituto Bibl....","fid":"page"}]}]}