{"stem":"anima","instances":[{"docId":"nbr__869-33-16","docUri":"nbr__869-33-16.html","score":1,"contexts":[{"form":"animae","weight":"1","pos":461,"context":"...conscientiam jam satis angustiatam pauperrimi sacerdotis, qui vulnera <mark>animae<\/mark> suae Confessario suo sincere detegere non verecundatur, sed...","fid":"p__8"}]},{"docId":"nbr__869-33-12","docUri":"nbr__869-33-12.html","score":1,"contexts":[{"form":"animae","weight":"1","pos":158,"context":"...acceptarem; in dedecus et damnum Ecclesiae et ruinam <mark>animae<\/mark> meae.","fid":"p__4"}]}]}