{"stem":"anzunehmen","instances":[{"docId":"nbr__869-33-15","docUri":"nbr__869-33-15.html","score":1,"contexts":[{"form":"anzunehmen","weight":"1","pos":72,"context":"...dar, die ihn davon abhalten, die Würde <mark>anzunehmen<\/mark>. Er habe hinzugefügt, dass er gewillt sei...","fid":"p__1"}]},{"docId":"nbr__869-33-46","docUri":"nbr__869-33-46.html","score":1,"contexts":[{"form":"anzunehmen","weight":"1","pos":70,"context":"...des Msgr. Wenzel Grosam, diese Beförderung nicht <mark>anzunehmen<\/mark>, in Wirklichkeit nicht existieren würden. Zu Msgr....","fid":"p__1"}]}]}