{"stem":"ben","instances":[{"docId":"nbr__848-20-71","docUri":"nbr__848-20-71.html","score":6,"contexts":[{"form":"ben","weight":"1","pos":1167,"context":"...e della stessa Alma Mater, frequentata ora da <mark>ben<\/mark> 12,000 studenti, dei quali circa 5000 inscritti alla...","fid":"p__10"},{"form":"ben","weight":"1","pos":1219,"context":"...dell’apatia e dell’incomprensione, e l’avversario ne abusa, <mark>ben<\/mark> si sa, per i suoi malevoli scopi.","fid":"p__6"},{"form":"ben","weight":"1","pos":1616,"context":".... Invece le statistiche delle associazioni cattoliche femminili lasciano <mark>ben<\/mark> più a desiderare, e la federazione diocesana,...","fid":"p__12"},{"form":"ben","weight":"1","pos":4213,"context":"...e 363 gruppi. L’incasso nell’ultimo anno fu di <mark>ben<\/mark> quattro millioni di Schilling (1 Sch. = a...","fid":"p__6"},{"form":"ben","weight":"1","pos":4306,"context":"..., tanto cara ai fanciulli, e vi intervennero <mark>ben<\/mark> 30,000 bambini! Non si possono riferire senza un...","fid":"p__10"},{"form":"ben","weight":"1","pos":4329,"context":"Parlò poi della letteratura socialista, che <mark>ben<\/mark> si può definire: irreligione, immoralità, glorificazione...","fid":"p__19"}]},{"docId":"nbr__852-23-69","docUri":"nbr__852-23-69.html","score":1,"contexts":[{"form":"ben","weight":"1","pos":671,"context":"...disordini, ad affrontare i quali questo Governo è <mark>ben<\/mark> preparato per reprimerli; e che piuttosto possano sperarsi...","fid":"p__19"}]},{"docId":"nbr__852-25-75","docUri":"nbr__852-25-75.html","score":1,"contexts":[{"form":"ben","weight":"1","pos":458,"context":"Il Governo però, che era <mark>ben<\/mark> preparato ad ogni emergenza, fece chiudere manu militari...","fid":"p__10"}]},{"docId":"nbr__848-21-41","docUri":"nbr__848-21-41.html","score":1,"contexts":[{"form":"ben","weight":"1","pos":432,"context":"...socialismo; ma su di ciò ho già per <mark>ben<\/mark> tre volte richiamata tutta l’attenzione di questo Emmo....","fid":"p__6"}]},{"docId":"nbr__869-33-46","docUri":"nbr__869-33-46.html","score":1,"contexts":[{"form":"ben","weight":"1","pos":540,"context":"Al mio parere sarebbe anche lui <mark>ben<\/mark> idoneo e degno di essere promosso alla dignità della...","fid":"p__9"}]}]}