{"stem":"coscienza","instances":[{"docId":"nbr__848-20-71","docUri":"nbr__848-20-71.html","score":2,"contexts":[{"form":"coscienza","weight":"1","pos":2505,"context":"...Presidente e di Cancelliere. Quindi un conflitto di <mark>coscienza<\/mark>, che lo dispensa a chiedere già più volte...","fid":"p__15"},{"form":"coscienza","weight":"1","pos":2954,"context":"A tener viva e ad educare la <mark>coscienza<\/mark> cattolica sono necessarie più chiese e più scuole,...","fid":"p__4"}]},{"docId":"nbr__869-33-46","docUri":"nbr__869-33-46.html","score":1,"contexts":[{"form":"coscienza","weight":"1","pos":704,"context":"...che credo possa dare con tutta la responsabilità di <mark>coscienza<\/mark> in un affare di sommo momento.","fid":"p__10"}]}]}