{"stem":"dell'ordin","instances":[{"docId":"nbr__852-25-75","docUri":"nbr__852-25-75.html","score":1,"contexts":[{"form":"dell’ordine","weight":"1","pos":512,"context":"...a prendere senza riguardi forti misure contro i perturbatori <mark>dell’ordine<\/mark> pubblico e a migliorare la situazione economica, come...","fid":"p__10"}]},{"docId":"nbr__848-20-71","docUri":"nbr__848-20-71.html","score":1,"contexts":[{"form":"dell’ordine","weight":"1","pos":3899,"context":"..., e deplora i traviamenti del pensiero in danno <mark>dell’ordine<\/mark> e della morale cristiana.","fid":"p__4"}]}]}