{"stem":"dell'anno","instances":[{"docId":"848-20-71","docUri":"848-20-71.html","score":2,"contexts":[{"form":"dell’anno","weight":"1","pos":2639,"context":"...nell’ultimo tempo, specialmente dopo le Missioni del novembre <mark>dell’anno<\/mark> scorso, che sebbene vi avessero partecipato solo il...","fid":"p__13"},{"form":"dell’anno","weight":"1","pos":2946,"context":"Il numero delle apostasie aumenta, nell’aprile <mark>dell’anno<\/mark> corr. Si ebbero 1200 casi, nel maggio...","fid":"p__8"}]}]}