{"stem":"deputatus","instances":[{"docId":"nbr__869-33-46","docUri":"nbr__869-33-46.html","score":2,"contexts":[{"form":"deputatus","weight":"1","pos":127,"context":"...noch Generalsekretär der „Unione Leonina“ und „Consiliarius <mark>deputatus<\/mark> pro administratione temporalium“ des Diözesanseminars. Im Jahr 1908...","fid":"p__1"},{"form":"deputatus","weight":"1","pos":436,"context":"...Leonina” (Società scientifica a Vienna) e consiliarius <mark>deputatus<\/mark> pro administratione temporalium seminariorum archidioecesis. È prelato domestico...","fid":"p__4"}]}]}