{"stem":"disordini","instances":[{"docId":"nbr__852-23-69","docUri":"nbr__852-23-69.html","score":1,"contexts":[{"form":"disordini","weight":"1","pos":666,"context":"..., né spargimento di sangue, all’infuori di probabili <mark>disordini<\/mark>, ad affrontare i quali questo Governo è ben...","fid":"p__19"}]},{"docId":"nbr__852-23-73","docUri":"nbr__852-23-73.html","score":1,"contexts":[{"form":"disordini","weight":"1","pos":478,"context":"...e si può esser sicuri che non avverranno gravi <mark>disordini<\/mark> e che molto meno correnti di sinistra abbiano il...","fid":"p__12"}]},{"docId":"nbr__852-25-78","docUri":"nbr__852-25-78.html","score":1,"contexts":[{"form":"disordini","weight":"1","pos":153,"context":"...non ostante qualche tentativo dei Socialisti nazionali di provocare <mark>disordini<\/mark> (frustrato però con prontezza ed energia dalla forza...","fid":"p__4"}]},{"docId":"nbr__852-24-4","docUri":"nbr__852-24-4.html","score":1,"contexts":[{"form":"disordini","weight":"1","pos":310,"context":"...molto tranquilla, e non prevede l’eventualità di gravi <mark>disordini<\/mark>.","fid":"p__7"}]}]}