{"stem":"erklär","instances":[{"docId":"869-33-50","docUri":"869-33-50.html","score":1,"contexts":[{"form":"erkläre","weight":"1","pos":85,"context":"...geforderten Informationen: P. Bea äußere sich positiv, <mark>erkläre<\/mark> aber nicht umfassend informiert zu sein (Nr. 6). Der...","fid":"p__4"}]},{"docId":"869-33-12","docUri":"869-33-12.html","score":1,"contexts":[{"form":"erkläre","weight":"1","pos":71,"context":"...zu Füßen des Kreuzes Jesus Christi gekniet, und <mark>erkläre<\/mark> mit gestärktem Geist, dass er seine Zustimmung weder...","fid":"p__1"}]}]}