{"stem":"gehört","instances":[{"docId":"nbr__852-23-73","docUri":"nbr__852-23-73.html","score":1,"contexts":[{"form":"gehört","weight":"1","pos":128,"context":"...Schulen angehe. Dies habe er gesagt, weil er <mark>gehört<\/mark> habe, dass es von den Großdeutschen Druck gegeben habe,...","fid":"p__1"}]},{"docId":"nbr__848-20-71","docUri":"nbr__848-20-71.html","score":1,"contexts":[{"form":"gehört","weight":"1","pos":72,"context":"...Stimmen der Bischöfe unter der Leitung von Kardinal Piffl <mark>gehört<\/mark> werden würde. Der Autor attestiert einen Mangel an Kirchen...","fid":"p__1"}]},{"docId":"nbr__852-25-78","docUri":"nbr__852-25-78.html","score":1,"contexts":[{"form":"gehört","weight":"1","pos":88,"context":"..., des Heeresministers Vaugoin und des Justizministers Dr. Schußnigg <mark>gehört<\/mark>. Auch Msgr. Filzer der Weihbischof von Salzburg...","fid":"p__1"}]}]}