{"stem":"giovanil","instances":[{"docId":"822-16-24","docUri":"822-16-24.html","score":1,"contexts":[{"form":"giovanile","weight":"1","pos":135,"context":"...difendere presso codesta Segreteria di Stato di S.S. l’associazione <mark>giovanile<\/mark> “Neuland”, di cui nel venerato Dispaccio N. 1760...","fid":"p__3"}]},{"docId":"848-20-71","docUri":"848-20-71.html","score":1,"contexts":[{"form":"giovanile","weight":"1","pos":4130,"context":"...nello studio delle associazioni e di tutto il movimento <mark>giovanile<\/mark>, sia cattolico e sia avversario. Gli stessi...","fid":"p__2"}]},{"docId":"848-21-41","docUri":"848-21-41.html","score":1,"contexts":[{"form":"giovanile","weight":"1","pos":403,"context":"..., forse cinque o sei, i quali provenienti dalla <mark>giovanile<\/mark> associazione cattolica il “Neuland”, hanno dimostrato e dimostrano...","fid":"p__6"}]}]}