{"stem":"istituti","instances":[{"docId":"nbr__848-20-71","docUri":"nbr__848-20-71.html","score":2,"contexts":[{"form":"istituti","weight":"1","pos":923,"context":"Alla mancanza di clero vanno supplendo gli <mark>istituti<\/mark> diocesani e l’opera delle vocazioni ecclesiastiche di S. Pietro...","fid":"p__7"},{"form":"istituti","weight":"1","pos":1158,"context":"I socialisti aspirano anche alla conquista degli <mark>istituti<\/mark> scolastici superiori e della stessa Alma Mater, frequentata...","fid":"p__10"}]}]}