{"stem":"keinerlei","instances":[{"docId":"nbr__852-23-73","docUri":"nbr__852-23-73.html","score":1,"contexts":[{"form":"keinerlei","weight":"1","pos":160,"context":"...Arzt in eine Klinik eingewiesen worden, mit der Auflage <mark>keinerlei<\/mark> Arbeit zu verrichten und keine Besuche zu empfangen....","fid":"p__1"}]},{"docId":"nbr__848-21-40","docUri":"nbr__848-21-40.html","score":1,"contexts":[{"form":"keinerlei","weight":"1","pos":81,"context":"...Aufenthalt in Rom seiner Sache zuversichtlich gezeigt und auch <mark>keinerlei<\/mark> Klage über die Einstellung des Klerus vorgebracht, man...","fid":"p__1"}]}]}