{"stem":"pater","instances":[{"docId":"869-33-16","docUri":"869-33-16.html","score":3,"contexts":[{"form":"Pater","weight":"1","pos":2,"context":" Beatissime <mark>Pater<\/mark>!           Iterum veniam et misericordiam Sanctitatis Vestrae implorat filius...","fid":"page"},{"form":"Pater","weight":"1","pos":269,"context":"Tertio tandem: Beatissime <mark>Pater<\/mark>, per viscera misericordiae Jesu Christi rogo, ne...","fid":"p__8"},{"form":"Pater","weight":"1","pos":375,"context":"Parce mihi, Sanctissime <mark>Pater<\/mark>, aliumque dignare eligere, qui pascat Ecclesiam Viennensem...","fid":"p__12"}]},{"docId":"869-33-12","docUri":"869-33-12.html","score":1,"contexts":[{"form":"Pater","weight":"1","pos":74,"context":"Parcat Beatissimus <mark>Pater<\/mark>, Sanctissimus Dominus Noster; ignoscat Excellentia Vestra Illma...","fid":"p__5"}]}]}