{"stem":"politici","instances":[{"docId":"822-15-28","docUri":"822-15-28.html","score":1,"contexts":[{"form":"politici","weight":"1","pos":73,"context":"...essere libero da quella vecchia mentalità degli antichi partiti <mark>politici<\/mark>.","fid":"p__3"}]},{"docId":"852-25-47","docUri":"852-25-47.html","score":1,"contexts":[{"form":"politici","weight":"1","pos":283,"context":"...si dice, ad un Ministero forte dei migliori <mark>politici<\/mark> austriaci, che abbiano il coraggio di governare senza...","fid":"p__10"}]}]}