{"stem":"riscontro","instances":[{"docId":"852-24-4","docUri":"852-24-4.html","score":2,"contexts":[{"form":"Riscontro","weight":"1","pos":2,"context":" Oggetto: <mark>Riscontro<\/mark> al dispaccio N. 2365\/29 e Notizie politiche Eminenza...","fid":"page"},{"form":"riscontro","weight":"1","pos":59,"context":"...Ottobre u.s. N. 11.275\/412, cui è <mark>riscontro<\/mark> il su citato dispaccio, compio il dovere di...","fid":"p__4"}]},{"docId":"869-33-11","docUri":"869-33-11.html","score":1,"contexts":[{"form":"Riscontro","weight":"1","pos":2,"context":" Oggetto: <mark>Riscontro<\/mark> al cifrato N. 28. Eminenza Reverendissima,   Inchinato al...","fid":"page"}]},{"docId":"848-21-41","docUri":"848-21-41.html","score":1,"contexts":[{"form":"Riscontro","weight":"1","pos":2,"context":" Oggetto: <mark>Riscontro<\/mark> al Cifrato N.1613\/33. Eminenza Reverendissima,       Inchinato...","fid":"page"}]}]}