{"stem":"santo","instances":[{"docId":"848-20-71","docUri":"848-20-71.html","score":4,"contexts":[{"form":"Santo","weight":"1","pos":2078,"context":"...visita pastorale, e si mostrò vivamente grato al <mark>Santo<\/mark> Padre per le Sue continue solerti premure.","fid":"p__2"},{"form":"Santo","weight":"1","pos":2318,"context":"...attaccamento e di devozione alla Santa Sede ed al <mark>Santo<\/mark> Padre, da cui disse di molto sperare per...","fid":"p__3"},{"form":"Santo","weight":"1","pos":2691,"context":"...conforto, soggiunge, il mai cessato interessamento del <mark>Santo<\/mark> Padre alle nostre sorti, ed oggi potrebbe giovare...","fid":"p__10"},{"form":"Santo","weight":"1","pos":3433,"context":"..., di cui è stato testè fatto omaggio al <mark>Santo<\/mark> Padre.","fid":"p__7"}]},{"docId":"848-21-40","docUri":"848-21-40.html","score":1,"contexts":[{"form":"Santo","weight":"1","pos":206,"context":"...l’attitudine del Clero, tuttavia per venerato incarico del <mark>Santo<\/mark> Padre, prego Vostra Eccellenza Rev.ma a darmi...","fid":"p__14"}]},{"docId":"869-33-65","docUri":"869-33-65.html","score":1,"contexts":[{"form":"Santo","weight":"1","pos":205,"context":"...del nuovo Arcivescovo, esprime la sua riconoscenza al <mark>Santo<\/mark> Padre per essersi degnato di dare a questa insigne...","fid":"p__4"}]},{"docId":"848-20-47","docUri":"848-20-47.html","score":1,"contexts":[{"form":"Santo","weight":"1","pos":137,"context":".... Nullaosta venuta Cancelliere purchè egli venga prima dal <mark>Santo<\/mark> Padre.","fid":"p__3"}]},{"docId":"869-33-37","docUri":"869-33-37.html","score":1,"contexts":[{"form":"Santo","weight":"1","pos":84,"context":"Tra i candidati sui quali il <mark>Santo<\/mark> Padre ha fermata la sua augusta attenzione per la...","fid":"p__3"}]},{"docId":"869-33-11","docUri":"869-33-11.html","score":1,"contexts":[{"form":"Santo","weight":"1","pos":116,"context":"...perché egli accetti l’altissima dignità offertagli, se al <mark>Santo<\/mark> Padre così piacesse, sarebbe di obbligarlo ad accettare...","fid":"p__4"}]},{"docId":"869-33-35","docUri":"869-33-35.html","score":1,"contexts":[{"form":"Santo","weight":"1","pos":181,"context":"...in urgendis iis, quae necessaria sunt”, il <mark>Santo<\/mark> Padre, prima di prendere una decisione, interessa...","fid":"p__9"}]},{"docId":"869-33-41","docUri":"869-33-41.html","score":1,"contexts":[{"form":"Santo","weight":"1","pos":77,"context":"Il <mark>Santo<\/mark> Padre Si propone di elevare alla Sede arcivescovile di...","fid":"p__3"}]},{"docId":"852-23-73","docUri":"852-23-73.html","score":1,"contexts":[{"form":"Santo","weight":"1","pos":695,"context":"...di benedizione, recatagli dal Nunzio a nome del <mark>Santo<\/mark> Padre, che il Seipel ama svisceratamente, giungerebbe...","fid":"p__21"}]},{"docId":"852-25-43","docUri":"852-25-43.html","score":1,"contexts":[{"form":"Santo","weight":"1","pos":56,"context":"N. 22. <mark>Santo<\/mark> Padre si è degnato concedere indulto richiesto Rapporto N....","fid":"p__1"}]},{"docId":"869-33-15","docUri":"869-33-15.html","score":1,"contexts":[{"form":"Santo","weight":"1","pos":176,"context":"...che ha di accettare l’altissima dignità, cui il <mark>Santo<\/mark> Padre vorrebbe elevarlo, ed aggiungendo che sebbene sia...","fid":"p__5"}]}]}