{"stem":"santità","instances":[{"docId":"869-33-43","docUri":"869-33-43.html","score":3,"contexts":[{"form":"Santità","weight":"1","pos":8,"context":"Accingendomi a soddisfare al venerato incarico della <mark>Santità<\/mark> Vostra di dare il mio parere sull’Ill.mo e...","fid":"p__3"},{"form":"Santità","weight":"1","pos":268,"context":" Beatissimo Padre,      Prego la <mark>Santità<\/mark> Vostra di gradire questo umile mio parere in proposito...","fid":"page"},{"form":"Santità","weight":"1","pos":290,"context":"...Piede, imploro umilmente la benedizione apostolica. Della <mark>Santità<\/mark> Vostra Umilissimo Obbedientissimo Devotissimo Agostino Bea 5 ","fid":"page"}]},{"docId":"869-33-42","docUri":"869-33-42.html","score":2,"contexts":[{"form":"Santità","weight":"1","pos":8,"context":"Nella lettera acclusa presento a Sua <mark>Santità<\/mark> il mio umile parere sull’Ill.mo e Rev.mo...","fid":"p__3"},{"form":"Santità","weight":"1","pos":36,"context":"...Rev.ma di voler consegnare la lettera a Sua <mark>Santità<\/mark>.","fid":"p__3"}]},{"docId":"869-33-46","docUri":"869-33-46.html","score":2,"contexts":[{"form":"Santità","weight":"1","pos":32,"context":"...Mons. Teodoro Innitzer, nuovo candidato che Sua <mark>Santità<\/mark> intende elevare alla sede arcivescovile di Vienna, giacché...","fid":"p__5"},{"form":"Santità","weight":"1","pos":198,"context":"...temporalium seminariorum archidioecesis. È prelato domestico di Sua <mark>Santità<\/mark> (fin dall’anno 1931) e nell’anno 1930\/31...","fid":"p__4"}]},{"docId":"869-33-14","docUri":"869-33-14.html","score":1,"contexts":[{"form":"Santità","weight":"1","pos":25,"context":"...difficoltà positive e concrete, può esporle a Sua <mark>Santità<\/mark>.","fid":"p__6"}]},{"docId":"869-33-37","docUri":"869-33-37.html","score":1,"contexts":[{"form":"Santità","weight":"1","pos":60,"context":"...Prima, però, di procedere oltre, Sua <mark>Santità<\/mark> desidera avere da V. E. sul candidato in parola...","fid":"p__6"}]},{"docId":"848-20-46","docUri":"848-20-46.html","score":1,"contexts":[{"form":"Santità","weight":"1","pos":21,"context":"...Il 30 si porterebbero a Roma se Sua <mark>Santità<\/mark> si degnasse riceverlo lunedì 2 Aprile dovendo ritornare immediatamente...","fid":"p__5"}]},{"docId":"848-20-71","docUri":"848-20-71.html","score":1,"contexts":[{"form":"Santità","weight":"1","pos":1805,"context":"...nome suo e del suo Paese, a Sua <mark>Santità<\/mark>, ne implorava la Santa Benedizione.","fid":"p__3"}]},{"docId":"869-33-35","docUri":"869-33-35.html","score":1,"contexts":[{"form":"Santità","weight":"1","pos":13,"context":"...\/635 relativo a Mons. Grosam. Sua <mark>Santità<\/mark> non crede che sia più il caso di fare...","fid":"p__2"}]},{"docId":"869-33-41","docUri":"869-33-41.html","score":1,"contexts":[{"form":"Santità","weight":"1","pos":29,"context":"...però, di procedere alla nomina definitiva, Sua <mark>Santità<\/mark> desidera conoscere avere dalla P. V. Rma precise informazioni...","fid":"p__5"}]},{"docId":"869-33-15","docUri":"869-33-15.html","score":1,"contexts":[{"form":"Santità","weight":"1","pos":82,"context":"...preghiera di farla giungere nelle auguste Mani di Sua <mark>Santità<\/mark>, dicendomi che in essa espone le gravi difficoltà...","fid":"p__5"}]}]}