{"stem":"tener","instances":[{"docId":"nbr__848-20-71","docUri":"nbr__848-20-71.html","score":2,"contexts":[{"form":"tenere","weight":"1","pos":2859,"context":"...confida da molti nella “Heimwehr”, che forse potrà <mark>tenere<\/mark> in scacco i furori dei socialisti superando in numero...","fid":"p__2"},{"form":"tener","weight":"1","pos":2951,"context":"A <mark>tener<\/mark> viva e ad educare la coscienza cattolica sono necessarie...","fid":"p__4"}]},{"docId":"nbr__852-23-73","docUri":"nbr__852-23-73.html","score":1,"contexts":[{"form":"tenere","weight":"1","pos":379,"context":"...nelle scuole, che egli, mi disse, <mark>tenere<\/mark> sommamente a cuore, e che il Nunzio poteva...","fid":"p__9"}]}]}