{"stem":"venerato","instances":[{"docId":"nbr__869-33-15","docUri":"nbr__869-33-15.html","score":2,"contexts":[{"form":"venerato","weight":"1","pos":103,"context":"...ogni delicatezza l’incarico affidatomi dalla Emienenza Vostra Reverendissima col <mark>venerato<\/mark> cifrato N. 29 del 16 corrente mese; come...","fid":"p__5"},{"form":"venerato","weight":"1","pos":117,"context":"...ogni delicatezza eseguii quanto l’E.V.R. mi significava nell’altro <mark>venerato<\/mark> cifrato N. 28 del 9 luglio c.. c.m. ","fid":"p__5"}]},{"docId":"nbr__869-33-43","docUri":"nbr__869-33-43.html","score":1,"contexts":[{"form":"venerato","weight":"1","pos":158,"context":"Accingendomi a soddisfare al <mark>venerato<\/mark> incarico della Santità Vostra di dare il mio parere...","fid":"p__3"}]},{"docId":"nbr__848-20-71","docUri":"nbr__848-20-71.html","score":1,"contexts":[{"form":"venerato","weight":"1","pos":914,"context":"...coll’azione a riempire questo vuoto sotto l’illuminata guida del <mark>venerato<\/mark> Pastore diocesano.","fid":"p__3"}]},{"docId":"nbr__822-16-24","docUri":"nbr__822-16-24.html","score":1,"contexts":[{"form":"venerato","weight":"1","pos":139,"context":"...di S.S. l’associazione giovanile “Neuland”, di cui nel <mark>venerato<\/mark> Dispaccio N. 1760\/36 del 19 maggio.","fid":"p__3"}]},{"docId":"nbr__869-33-36","docUri":"nbr__869-33-36.html","score":1,"contexts":[{"form":"venerato","weight":"1","pos":147,"context":"Com’ebbi l’onore di ricevere il <mark>venerato<\/mark> dispaccio della Eminenza Vostra Reverendissima del 27 luglio u.s....","fid":"p__3"}]},{"docId":"nbr__848-21-41","docUri":"nbr__848-21-41.html","score":1,"contexts":[{"form":"venerato","weight":"1","pos":208,"context":"...ossequio a quanto l’Eminenza Vostra Reverendissima mi significa nel <mark>venerato<\/mark> dispaccio in cifra N. 1613\/33, ho voluto procurarmi...","fid":"p__3"}]},{"docId":"nbr__848-21-40","docUri":"nbr__848-21-40.html","score":1,"contexts":[{"form":"venerato","weight":"1","pos":203,"context":"...a lamento circa l’attitudine del Clero, tuttavia per <mark>venerato<\/mark> incarico del Santo Padre, prego Vostra Eccellenza Rev...","fid":"p__14"}]},{"docId":"nbr__852-24-4","docUri":"nbr__852-24-4.html","score":1,"contexts":[{"form":"venerato","weight":"1","pos":129,"context":"Ringrazio rispettosamente L’Eminenza Vostra reverendissima per il <mark>venerato<\/mark> dispaccio N. 2365\/29, in data 21 corrente,...","fid":"p__4"}]},{"docId":"nbr__869-33-11","docUri":"nbr__869-33-11.html","score":1,"contexts":[{"form":"venerato","weight":"1","pos":102,"context":"...), per espresso e raccomandata, appena pervenutomi il <mark>venerato<\/mark> cifrato di V.E.R. N. 28 del pomeriggio di sabato...","fid":"p__3"}]}]}