{"stem":"verbessern","instances":[{"docId":"852-25-75","docUri":"852-25-75.html","score":1,"contexts":[{"form":"verbessern","weight":"1","pos":180,"context":"...Störer der öffentlichen Ordnung fortführen und die wirtschaftliche Lage <mark>verbessern<\/mark>, wie sie es bisher mache, so stünden...","fid":"p__1"}]},{"docId":"848-20-71","docUri":"848-20-71.html","score":1,"contexts":[{"form":"verbessern","weight":"1","pos":227,"context":"...zwischen Italien, Ungarn und Österreich die wirtschaftliche Lage <mark>verbessern<\/mark> werde. Seiner Einschätzung nach würden die katholischen Organisationen florieren...","fid":"page"}]}]}