{"stem":"vuol","instances":[{"docId":"848-20-71","docUri":"848-20-71.html","score":3,"contexts":[{"form":"vuole","weight":"1","pos":96,"context":"...cardini, e la cara gioventù, che si <mark>vuole<\/mark> strappare ad ogni costo, e fino dai più...","fid":"p__6"},{"form":"vuole","weight":"1","pos":1669,"context":"...per fronteggiare i pericoli della situazione, che si <mark>vuole<\/mark> migliorare ad ogni costo. Mi indicò delle persone...","fid":"p__9"},{"form":"vuole","weight":"1","pos":3208,"context":"...ma il lavoro dovrà venir intensificato, se si <mark>vuole<\/mark> sanare la situazione estremamente grave sotto molti rispetti....","fid":"p__3"}]},{"docId":"848-21-41","docUri":"848-21-41.html","score":1,"contexts":[{"form":"vuol","weight":"1","pos":526,"context":"...: e sapendo già che l’Episcopato austriaco quasi unanime <mark>vuol<\/mark> soddisfare quel desiderio, riconoscendone la necessità per il...","fid":"p__8"}]},{"docId":"852-23-73","docUri":"852-23-73.html","score":1,"contexts":[{"form":"vuole","weight":"1","pos":365,"context":"...che Mgr. Seipel è gravemente malato e che <mark>vuole<\/mark> ritirarsi definitivamente a vita privata: e l’Arbeiterzeitung è...","fid":"p__15"}]},{"docId":"869-33-38","docUri":"869-33-38.html","score":1,"contexts":[{"form":"vuole","weight":"1","pos":52,"context":"...il Nunzio Apostolico di Vienna, rispose: “Che <mark>vuole<\/mark> che le dica? Si tratta di una mia...","fid":"p__5"}]}]}